[ {
  "id" : "QF9XhXnwNtobejyBxc-To",
  "images" : [ "\\images\\House1.jpg" ],
  "title" : "Traditional cabin",
  "address" : "Glumslövsvägen 23, 261 62",
  "zipcode" : null,
  "city" : "Glumslöv",
  "propertyType" : "Torp",
  "accommodation" : {
    "bathrooms" : 2,
    "beds" : 5
  },
  "description" : "Small cabin located on west coast",
  "price" : "3000",
  "amenities" : [ "Bed", "Breakfast", "Camera", "CCTV" ],
  "reviews" : null,
  "ownerId" : "eyzouy9Bwh_5crMvLmguX",
  "position" : [ 55.69370479244656, 13.908292932699233 ],
  "leaseStart" : null,
  "leaseEnd" : null,
  "bookings" : null
}, {
  "id" : "dcGqW973SuZ7J6OWJRs6z",
  "images" : [ "\\images\\House2.jpg" ],
  "title" : "Cozy log cabin",
  "address" : "Södra Bergönsvägen 10, 343 71",
  "zipcode" : null,
  "city" : "Glumslöv",
  "propertyType" : "Villa",
  "accommodation" : {
    "bathrooms" : 2,
    "beds" : 5
  },
  "description" : "Warm log cabin located close to nature",
  "price" : "3999",
  "amenities" : [ "Bed", "Breakfast", "Camera", "CCTV" ],
  "reviews" : null,
  "ownerId" : "eyzouy9Bwh_5crMvLmguX",
  "position" : [ 55.68370479244602, 13.608292932699289 ],
  "leaseStart" : null,
  "leaseEnd" : null,
  "bookings" : null
}, {
  "id" : "bVZlMEakb-184N0je24RI",
  "images" : [ "\\images\\House3.jpg" ],
  "title" : "Classic estate in nature",
  "address" : "Ivö Ljungaväg 95, 290 34",
  "zipcode" : null,
  "city" : "Glumslöv",
  "propertyType" : "Lägenhet",
  "accommodation" : {
    "bathrooms" : 1,
    "beds" : 3
  },
  "description" : "Beautiful, large estate close to lake and the east coast",
  "price" : "1000",
  "amenities" : [ "Bed", "Breakfast", "Camera", "CCTV" ],
  "reviews" : null,
  "ownerId" : "eyzouy9Bwh_5crMvLmguX",
  "position" : [ 55.68570479244602, 13.308292932699288 ],
  "leaseStart" : null,
  "leaseEnd" : null,
  "bookings" : null
}, {
  "id" : "NlrUnApOQNNvH6gzU2bfl",
  "images" : [ "\\images\\House4.jpg" ],
  "title" : "Beach front villa",
  "address" : "Andrénvägen 34, 276 45",
  "zipcode" : null,
  "city" : "Glumslöv",
  "propertyType" : "Torp",
  "accommodation" : {
    "bathrooms" : 2,
    "beds" : 4
  },
  "description" : "Fantastic villa close to amazing beaches",
  "price" : "2999",
  "amenities" : [ "Bed", "Breakfast", "Camera", "CCTV" ],
  "reviews" : null,
  "ownerId" : "gQFpv1DOCTnaWAjf02Em1",
  "position" : [ 55.78370479244602, 13.60829693269929 ],
  "leaseStart" : null,
  "leaseEnd" : null,
  "bookings" : null
}, {
  "id" : "spYROoShRiR-KDqU1piUK",
  "images" : [ "\\images\\House5.jpg" ],
  "title" : "Luxuary villa",
  "address" : "Hobjersvägen 17, 271 78",
  "zipcode" : null,
  "city" : "Ystad",
  "propertyType" : "Lägenhet",
  "accommodation" : {
    "bathrooms" : 2,
    "beds" : 6
  },
  "description" : "Modern villa with swimming pool, located five minutes from the beach",
  "price" : "4999",
  "amenities" : [ "Bed", "Breakfast", "Camera", "CCTV" ],
  "reviews" : null,
  "ownerId" : "gQFpv1DOCTnaWAjf02Em1",
  "position" : [ 55.61370479244602, 13.618292932699289 ],
  "leaseStart" : null,
  "leaseEnd" : null,
  "bookings" : null
}, {
  "id" : "twxJGpNW9NrVaF2b9O_fR",
  "images" : [ "\\images\\House6.jpg" ],
  "title" : "Large house for family",
  "address" : "Lachmannsväg 29, 271 72",
  "zipcode" : null,
  "city" : "Glumslöv",
  "propertyType" : "Sommarstuga",
  "accommodation" : {
    "bathrooms" : 2,
    "beds" : 7
  },
  "description" : "Perfect house for a large family vacation",
  "price" : "2800",
  "amenities" : [ "Dinner", "Elevator", "Fridge", "Heating" ],
  "reviews" : null,
  "ownerId" : "0erYFeQsbyxuxdxBNOyB_",
  "position" : [ 55.62370479244602, 13.628292932699289 ],
  "leaseStart" : null,
  "leaseEnd" : null,
  "bookings" : null
}, {
  "id" : "0cbPLpLgqsnqSB3H2uaKx",
  "images" : [ "\\images\\House7.jpg" ],
  "title" : "Cozy cottage",
  "address" : "Björnbärsgatan 9, 234 43 Lomma",
  "zipcode" : null,
  "city" : "Ystad",
  "propertyType" : "Sommarstuga",
  "accommodation" : {
    "bathrooms" : 2,
    "beds" : 3
  },
  "description" : "Located close to beaches and the city of Lund, perfect for a weekend getaway",
  "price" : "3350",
  "amenities" : [ "Dinner", "Elevator", "Fridge", "Heating" ],
  "reviews" : null,
  "ownerId" : "dBDpz9bDOYvP3E9cB2A-O",
  "position" : [ 55.63370479244602, 13.638292932699288 ],
  "leaseStart" : null,
  "leaseEnd" : null,
  "bookings" : null
}, {
  "id" : "o0U_oWPgWfmyFmeWjnyWk",
  "images" : [ "\\images\\House8.jpg" ],
  "title" : "Modern house in suburb",
  "address" : "Prästgången 2, 224 80 Lund",
  "zipcode" : null,
  "city" : "Lund",
  "propertyType" : "Lägenhet",
  "accommodation" : {
    "bathrooms" : 1,
    "beds" : 2
  },
  "description" : "Newly built large house for family vaccations",
  "price" : "1500",
  "amenities" : [ "Dinner", "Elevator", "Fridge", "Heating" ],
  "reviews" : null,
  "ownerId" : "dBDpz9bDOYvP3E9cB2A-O",
  "position" : [ 55.64370479244602, 13.648292932699288 ],
  "leaseStart" : null,
  "leaseEnd" : null,
  "bookings" : null
}, {
  "id" : "KqcgVlfUkMX5jxtqlIaAP",
  "images" : [ "\\images\\House9.jpg" ],
  "title" : "Guesthouse close to lake",
  "address" : "Vombsjövägen, 247 96 Veberöd",
  "zipcode" : null,
  "city" : "Lund",
  "propertyType" : "Lägenhet",
  "accommodation" : {
    "bathrooms" : 2,
    "beds" : 4
  },
  "description" : "Entire guesthouse for yourselves, comfortable in close proximity to lake Vomb",
  "price" : "2850",
  "amenities" : [ "Dinner", "Elevator", "Fridge", "Heating" ],
  "reviews" : null,
  "ownerId" : "_IwjSHxZHRvJmHtdLaSoZ",
  "position" : [ 55.68570479244602, 13.60129293269929 ],
  "leaseStart" : null,
  "leaseEnd" : null,
  "bookings" : null
}, {
  "id" : "2JTVem4JSjdl-u0CjGzxO",
  "images" : [ "\\images\\House10.jpg" ],
  "title" : "A room in Kivik",
  "address" : "Strandridarevägen 8-10, 277 30 Kivik",
  "zipcode" : null,
  "city" : "Lund",
  "propertyType" : "Villa",
  "accommodation" : {
    "bathrooms" : 2,
    "beds" : 3
  },
  "description" : "Welcome to a stay in our house",
  "price" : "1249",
  "amenities" : [ "Dinner", "Elevator", "Fridge", "Heating" ],
  "reviews" : null,
  "ownerId" : "0wyNX2Dv7ttJEnDvcnGxx",
  "position" : [ 55.68340479244602, 13.608592932699288 ],
  "leaseStart" : null,
  "leaseEnd" : null,
  "bookings" : null
}, {
  "id" : "8kHgfLziUXMXUN26vmI5-",
  "images" : [ "\\images\\House11.jpg" ],
  "title" : "Surfshack with fireplace",
  "address" : "Bakfamnen, 272 95",
  "zipcode" : null,
  "city" : "Glumslöv",
  "propertyType" : "Torp",
  "accommodation" : {
    "bathrooms" : 2,
    "beds" : 4
  },
  "description" : "Nice shack close to one of the best surfing spots in Sweden",
  "price" : "2670",
  "amenities" : [ "Bed", "Breakfast", "Camera", "CCTV" ],
  "reviews" : null,
  "ownerId" : "0wyNX2Dv7ttJEnDvcnGxx",
  "position" : [ 55.67370479244602, 13.65829293269929 ],
  "leaseStart" : null,
  "leaseEnd" : null,
  "bookings" : null
}, {
  "id" : "ejMnK0hcYhmp5RvWbQ8YL",
  "images" : [ "\\images\\House12.jpg" ],
  "title" : "Modern house",
  "address" : "Melycket 1, 272 95",
  "zipcode" : null,
  "city" : "Lund",
  "propertyType" : "Lägenhet",
  "accommodation" : {
    "bathrooms" : 2,
    "beds" : 3
  },
  "description" : "Newly built house in Vik, close to Simrishamn and Kivik",
  "price" : "3500",
  "amenities" : [ "Bed", "Breakfast", "Camera", "CCTV" ],
  "reviews" : null,
  "ownerId" : "Hf7pJLnRbu1uExXWaXRW2",
  "position" : [ 55.68379479244602, 13.60899293269929 ],
  "leaseStart" : null,
  "leaseEnd" : null,
  "bookings" : null
}, {
  "id" : "azG5NUzK3SDqQAkdcPmoe",
  "images" : [ "\\images\\House13.jpg" ],
  "title" : "Studio apartment in center",
  "address" : "Museigatan 15-1, 272 32",
  "zipcode" : null,
  "city" : "Lund",
  "propertyType" : "Sommarstuga",
  "accommodation" : {
    "bathrooms" : 2,
    "beds" : 3
  },
  "description" : "Renovated studio in the center of Simrishamn",
  "price" : "3200",
  "amenities" : [ "Bed", "Breakfast", "Camera", "CCTV" ],
  "reviews" : null,
  "ownerId" : "Hf7pJLnRbu1uExXWaXRW2",
  "position" : [ 55.60379479244602, 13.69029293269929 ],
  "leaseStart" : null,
  "leaseEnd" : null,
  "bookings" : null
}, {
  "id" : "5R0iSI8gc1rlO3thhD8dZ",
  "images" : [ "\\images\\House14.jpg" ],
  "title" : "Hostel in center",
  "address" : "Christian Barnekowsgatan 23, 272 32",
  "zipcode" : null,
  "city" : "Ystad",
  "propertyType" : "Torp",
  "accommodation" : {
    "bathrooms" : 2,
    "beds" : 5
  },
  "description" : "Clean and fresh hostel on the beautiful east coast of Scania",
  "price" : "2780",
  "amenities" : [ "Bed", "Breakfast", "Camera", "CCTV" ],
  "reviews" : null,
  "ownerId" : "ZNCHlkWXbVW-5ZzDahTHi",
  "position" : [ 55.68379999244602, 13.608291232699289 ],
  "leaseStart" : null,
  "leaseEnd" : null,
  "bookings" : null
}, {
  "id" : "qSZAPu9B5AIlXswIH5AID",
  "images" : [ "\\images\\House15.jpg" ],
  "title" : "Nice guesthouse close to sea",
  "address" : "Videgatan, 271 33",
  "zipcode" : null,
  "city" : "Ystad",
  "propertyType" : "Villa",
  "accommodation" : {
    "bathrooms" : 2,
    "beds" : 7
  },
  "description" : "Welcome to this guesthouse close to the sea and the well renowned spa",
  "price" : "4500",
  "amenities" : [ "Bed", "Breakfast", "Camera", "CCTV" ],
  "reviews" : null,
  "ownerId" : "vYdyudpjkIFH0ri1Y4Hh7",
  "position" : [ 55.68370479100602, 13.608292932200289 ],
  "leaseStart" : null,
  "leaseEnd" : null,
  "bookings" : null
}, {
  "id" : "DwhvsJqmzJ69QcUi9H2-4",
  "images" : [ "\\images\\House16.jpg" ],
  "title" : "Seaside cottage",
  "address" : "Skarpskyttevägen 92, 271 60",
  "zipcode" : null,
  "city" : "Ystad",
  "propertyType" : "Torp",
  "accommodation" : {
    "bathrooms" : 2,
    "beds" : 6
  },
  "description" : "Cute cottage with seaview and a 5 minute trip to the town of Ystad",
  "price" : "2100",
  "amenities" : [ "Bed", "Breakfast", "Camera", "CCTV" ],
  "reviews" : null,
  "ownerId" : "vYdyudpjkIFH0ri1Y4Hh7",
  "position" : [ 55.68370412244602, 13.608122932699288 ],
  "leaseStart" : null,
  "leaseEnd" : null,
  "bookings" : null
}, {
  "id" : "thZ4l05-Au8YOorGzQvTV",
  "images" : [ "\\images\\House17.jpg" ],
  "title" : "Apartment in the center",
  "address" : "Lilla Strandgatan 7, 271 43",
  "zipcode" : null,
  "city" : "Ystad",
  "propertyType" : "Lägenhet",
  "accommodation" : {
    "bathrooms" : 2,
    "beds" : 4
  },
  "description" : "Apartment right in the center of Ystad, close to everything",
  "price" : "1500",
  "amenities" : [ "Dinner", "Elevator", "Fridge", "Heating" ],
  "reviews" : null,
  "ownerId" : "vYdyudpjkIFH0ri1Y4Hh7",
  "position" : [ 55.68371279244602, 13.608122932699288 ],
  "leaseStart" : null,
  "leaseEnd" : null,
  "bookings" : null
}, {
  "id" : "qVLuiQBIvPh9XorvdkKZy",
  "images" : [ "\\images\\House18.jpg" ],
  "title" : "Renovated fishing lodge",
  "address" : "231 78 Smygehamn",
  "zipcode" : null,
  "city" : "Trelleborg",
  "propertyType" : "Villa",
  "accommodation" : {
    "bathrooms" : 2,
    "beds" : 7
  },
  "description" : "Refreshing getaway in quiet fishing village",
  "price" : "4100",
  "amenities" : [ "Dinner", "Elevator", "Fridge", "Heating" ],
  "reviews" : null,
  "ownerId" : "EryPZ1tDNIVv--19Q5H6u",
  "position" : [ 55.68376779244602, 13.608296732699289 ],
  "leaseStart" : null,
  "leaseEnd" : null,
  "bookings" : null
}, {
  "id" : "GFvR2-OznKv0L0DezBQ5u",
  "images" : [ "\\images\\House19.jpg" ],
  "title" : "Entire apartment",
  "address" : "Östergatan 49-65, 239 30",
  "zipcode" : null,
  "city" : "Trelleborg",
  "propertyType" : "Sommarstuga",
  "accommodation" : {
    "bathrooms" : 2,
    "beds" : 5
  },
  "description" : "Perfect for birdwatchers and close to golfing",
  "price" : "3100",
  "amenities" : [ "Dinner", "Elevator", "Fridge", "Heating" ],
  "reviews" : null,
  "ownerId" : "EryPZ1tDNIVv--19Q5H6u",
  "position" : [ 55.45370479244602, 13.458292932699289 ],
  "leaseStart" : null,
  "leaseEnd" : null,
  "bookings" : null
}, {
  "id" : "_VLfon8nLSNUDXDRENJd9",
  "images" : [ "\\images\\House20.jpg" ],
  "title" : "Entire estate in center",
  "address" : "Regementsgatan 52, 217 48",
  "zipcode" : null,
  "city" : "Trelleborg",
  "propertyType" : "Villa",
  "accommodation" : {
    "bathrooms" : 2,
    "beds" : 8
  },
  "description" : "Nice estate close to everything in Trellehulla",
  "price" : "4000",
  "amenities" : [ "Dinner", "Elevator", "Fridge", "Heating" ],
  "reviews" : null,
  "ownerId" : "EryPZ1tDNIVv--19Q5H6u",
  "position" : [ 55.68374579244602, 13.64529293269929 ],
  "leaseStart" : null,
  "leaseEnd" : null,
  "bookings" : null
} ]